llama_index/storage/chat_store/postgres/__init__.py
llama_index/storage/chat_store/postgres/base.py
llama_index_storage_chat_store_postgres-0.3.2.dist-info/METADATA
llama_index_storage_chat_store_postgres-0.3.2.dist-info/WHEEL
llama_index_storage_chat_store_postgres-0.3.2.dist-info/licenses/LICENSE
llama_index_storage_chat_store_postgres-0.3.2.dist-info/RECORD
