Metadata-Version: 2.4
Name: llama-index-storage-chat-store-postgres
Version: 0.3.2
Summary: llama-index storage-chat-store postgres integration
Author-email: Your Name <you@example.com>
License-Expression: MIT
License-File: LICENSE
Requires-Python: <4.0,>=3.9
Requires-Dist: asyncpg<0.31,>=0.30.0
Requires-Dist: llama-index-core<0.15,>=0.13.0
Requires-Dist: psycopg<4,>=3.0.0
